package daoImpl;

import dao.FileDao;
import entity.Store;
import java.sql.Connection;
import java.sql.ResultSet;
import java.sql.SQLException;
import java.sql.Statement;
import org.apache.log4j.Logger;
import utils.JdbcUtilsProperties;

public class FileDaoImpl
  implements FileDao
{
  public static Logger logger1 = Logger.getLogger(FileDaoImpl.class);
  
  /* Error */
  public void addFile(int id, String path, java.util.Date time, String name)
  {
    // Byte code:
    //   0: aconst_null
    //   1: astore 5
    //   3: aconst_null
    //   4: astore 6
    //   6: new 29	java/sql/Date
    //   9: dup
    //   10: aload_3
    //   11: invokevirtual 31	java/util/Date:getYear	()I
    //   14: aload_3
    //   15: invokevirtual 37	java/util/Date:getMonth	()I
    //   18: aload_3
    //   19: invokevirtual 40	java/util/Date:getDate	()I
    //   22: invokespecial 43	java/sql/Date:<init>	(III)V
    //   25: astore 7
    //   27: new 46	java/lang/StringBuilder
    //   30: dup
    //   31: ldc 48
    //   33: invokespecial 50	java/lang/StringBuilder:<init>	(Ljava/lang/String;)V
    //   36: iload_1
    //   37: invokevirtual 53	java/lang/StringBuilder:append	(I)Ljava/lang/StringBuilder;
    //   40: ldc 57
    //   42: invokevirtual 59	java/lang/StringBuilder:append	(Ljava/lang/String;)Ljava/lang/StringBuilder;
    //   45: aload_2
    //   46: invokevirtual 59	java/lang/StringBuilder:append	(Ljava/lang/String;)Ljava/lang/StringBuilder;
    //   49: ldc 57
    //   51: invokevirtual 59	java/lang/StringBuilder:append	(Ljava/lang/String;)Ljava/lang/StringBuilder;
    //   54: aload 7
    //   56: invokevirtual 62	java/lang/StringBuilder:append	(Ljava/lang/Object;)Ljava/lang/StringBuilder;
    //   59: ldc 57
    //   61: invokevirtual 59	java/lang/StringBuilder:append	(Ljava/lang/String;)Ljava/lang/StringBuilder;
    //   64: aload 4
    //   66: invokevirtual 59	java/lang/StringBuilder:append	(Ljava/lang/String;)Ljava/lang/StringBuilder;
    //   69: ldc 65
    //   71: invokevirtual 59	java/lang/StringBuilder:append	(Ljava/lang/String;)Ljava/lang/StringBuilder;
    //   74: invokevirtual 67	java/lang/StringBuilder:toString	()Ljava/lang/String;
    //   77: astore 8
    //   79: invokestatic 71	utils/JdbcUtilsProperties:getConnection	()Ljava/sql/Connection;
    //   82: astore 5
    //   84: aload 5
    //   86: invokeinterface 77 1 0
    //   91: astore 6
    //   93: aload 6
    //   95: aload 8
    //   97: invokeinterface 83 2 0
    //   102: pop
    //   103: goto +32 -> 135
    //   106: astore 9
    //   108: aload 9
    //   110: invokevirtual 89	java/sql/SQLException:printStackTrace	()V
    //   113: new 94	java/lang/RuntimeException
    //   116: dup
    //   117: ldc 96
    //   119: invokespecial 98	java/lang/RuntimeException:<init>	(Ljava/lang/String;)V
    //   122: athrow
    //   123: astore 10
    //   125: aload 5
    //   127: aload 6
    //   129: invokestatic 99	utils/JdbcUtilsProperties:close	(Ljava/sql/Connection;Ljava/sql/Statement;)V
    //   132: aload 10
    //   134: athrow
    //   135: aload 5
    //   137: aload 6
    //   139: invokestatic 99	utils/JdbcUtilsProperties:close	(Ljava/sql/Connection;Ljava/sql/Statement;)V
    //   142: return
    // Line number table:
    //   Java source line #25	-> byte code offset #0
    //   Java source line #26	-> byte code offset #3
    //   Java source line #27	-> byte code offset #6
    //   Java source line #28	-> byte code offset #27
    //   Java source line #29	-> byte code offset #45
    //   Java source line #28	-> byte code offset #74
    //   Java source line #30	-> byte code offset #79
    //   Java source line #32	-> byte code offset #84
    //   Java source line #33	-> byte code offset #93
    //   Java source line #34	-> byte code offset #106
    //   Java source line #35	-> byte code offset #108
    //   Java source line #36	-> byte code offset #113
    //   Java source line #37	-> byte code offset #123
    //   Java source line #38	-> byte code offset #125
    //   Java source line #39	-> byte code offset #132
    //   Java source line #38	-> byte code offset #135
    //   Java source line #40	-> byte code offset #142
    // Local variable table:
    //   start	length	slot	name	signature
    //   0	143	0	this	FileDaoImpl
    //   0	143	1	id	int
    //   0	143	2	path	String
    //   0	143	3	time	java.util.Date
    //   0	143	4	name	String
    //   1	135	5	con	Connection
    //   4	134	6	statement	Statement
    //   25	30	7	date	java.sql.Date
    //   77	19	8	sql	String
    //   106	3	9	e	SQLException
    //   123	10	10	localObject	Object
    // Exception table:
    //   from	to	target	type
    //   84	103	106	java/sql/SQLException
    //   84	123	123	finally
  }
  
  public int isExist(Store store, String path)
  {
    Connection con = null;
    Statement statement = null;
    ResultSet rs = null;
    String sql = "SELECT * FROM file WHERE storeId = '" + store.getStoreId() + 
      "'and filePath = '" + path + "'";
    con = JdbcUtilsProperties.getConnection();
    try
    {
      statement = con.createStatement();
      rs = statement.executeQuery(sql);
      if (rs.next())
      {
        int fileId = rs.getInt("fileId");
        return fileId;
      }
      return -1;
    }
    catch (SQLException e)
    {
      e.printStackTrace();
      throw new RuntimeException("文件---->查询数据失败");
    }
    finally
    {
      JdbcUtilsProperties.close(con, statement, rs);
    }
  }
  
  /* Error */
  public void upDateFile(Store store, String path, java.util.Date date, int fileId)
  {
    // Byte code:
    //   0: new 29	java/sql/Date
    //   3: dup
    //   4: aload_3
    //   5: invokevirtual 31	java/util/Date:getYear	()I
    //   8: aload_3
    //   9: invokevirtual 37	java/util/Date:getMonth	()I
    //   12: aload_3
    //   13: invokevirtual 40	java/util/Date:getDate	()I
    //   16: invokespecial 43	java/sql/Date:<init>	(III)V
    //   19: astore 5
    //   21: new 46	java/lang/StringBuilder
    //   24: dup
    //   25: ldc -93
    //   27: invokespecial 50	java/lang/StringBuilder:<init>	(Ljava/lang/String;)V
    //   30: aload_2
    //   31: invokevirtual 59	java/lang/StringBuilder:append	(Ljava/lang/String;)Ljava/lang/StringBuilder;
    //   34: ldc -91
    //   36: invokevirtual 59	java/lang/StringBuilder:append	(Ljava/lang/String;)Ljava/lang/StringBuilder;
    //   39: aload 5
    //   41: invokevirtual 62	java/lang/StringBuilder:append	(Ljava/lang/Object;)Ljava/lang/StringBuilder;
    //   44: ldc -89
    //   46: invokevirtual 59	java/lang/StringBuilder:append	(Ljava/lang/String;)Ljava/lang/StringBuilder;
    //   49: iload 4
    //   51: invokevirtual 53	java/lang/StringBuilder:append	(I)Ljava/lang/StringBuilder;
    //   54: ldc -121
    //   56: invokevirtual 59	java/lang/StringBuilder:append	(Ljava/lang/String;)Ljava/lang/StringBuilder;
    //   59: invokevirtual 67	java/lang/StringBuilder:toString	()Ljava/lang/String;
    //   62: astore 6
    //   64: aconst_null
    //   65: astore 7
    //   67: aconst_null
    //   68: astore 8
    //   70: invokestatic 71	utils/JdbcUtilsProperties:getConnection	()Ljava/sql/Connection;
    //   73: astore 7
    //   75: aload 7
    //   77: invokeinterface 77 1 0
    //   82: astore 8
    //   84: aload 8
    //   86: aload 6
    //   88: invokeinterface 83 2 0
    //   93: pop
    //   94: goto +32 -> 126
    //   97: astore 9
    //   99: aload 9
    //   101: invokevirtual 89	java/sql/SQLException:printStackTrace	()V
    //   104: new 94	java/lang/RuntimeException
    //   107: dup
    //   108: ldc -87
    //   110: invokespecial 98	java/lang/RuntimeException:<init>	(Ljava/lang/String;)V
    //   113: athrow
    //   114: astore 10
    //   116: aload 7
    //   118: aload 8
    //   120: invokestatic 99	utils/JdbcUtilsProperties:close	(Ljava/sql/Connection;Ljava/sql/Statement;)V
    //   123: aload 10
    //   125: athrow
    //   126: aload 7
    //   128: aload 8
    //   130: invokestatic 99	utils/JdbcUtilsProperties:close	(Ljava/sql/Connection;Ljava/sql/Statement;)V
    //   133: return
    // Line number table:
    //   Java source line #69	-> byte code offset #0
    //   Java source line #70	-> byte code offset #21
    //   Java source line #71	-> byte code offset #64
    //   Java source line #72	-> byte code offset #67
    //   Java source line #73	-> byte code offset #70
    //   Java source line #75	-> byte code offset #75
    //   Java source line #76	-> byte code offset #84
    //   Java source line #77	-> byte code offset #97
    //   Java source line #78	-> byte code offset #99
    //   Java source line #79	-> byte code offset #104
    //   Java source line #80	-> byte code offset #114
    //   Java source line #81	-> byte code offset #116
    //   Java source line #82	-> byte code offset #123
    //   Java source line #81	-> byte code offset #126
    //   Java source line #83	-> byte code offset #133
    // Local variable table:
    //   start	length	slot	name	signature
    //   0	134	0	this	FileDaoImpl
    //   0	134	1	store	Store
    //   0	134	2	path	String
    //   0	134	3	date	java.util.Date
    //   0	134	4	fileId	int
    //   19	21	5	time	java.sql.Date
    //   62	25	6	sql	String
    //   65	62	7	con	Connection
    //   68	61	8	statement	Statement
    //   97	3	9	e	SQLException
    //   114	10	10	localObject	Object
    // Exception table:
    //   from	to	target	type
    //   75	94	97	java/sql/SQLException
    //   75	114	114	finally
  }
  
  /* Error */
  public java.util.List<String> getAllFiles(int storeId)
  {
    // Byte code:
    //   0: new 175	java/util/ArrayList
    //   3: dup
    //   4: invokespecial 177	java/util/ArrayList:<init>	()V
    //   7: astore_2
    //   8: aconst_null
    //   9: astore_3
    //   10: aconst_null
    //   11: astore 4
    //   13: aconst_null
    //   14: astore 5
    //   16: new 46	java/lang/StringBuilder
    //   19: dup
    //   20: ldc -78
    //   22: invokespecial 50	java/lang/StringBuilder:<init>	(Ljava/lang/String;)V
    //   25: iload_1
    //   26: invokevirtual 53	java/lang/StringBuilder:append	(I)Ljava/lang/StringBuilder;
    //   29: ldc -121
    //   31: invokevirtual 59	java/lang/StringBuilder:append	(Ljava/lang/String;)Ljava/lang/StringBuilder;
    //   34: invokevirtual 67	java/lang/StringBuilder:toString	()Ljava/lang/String;
    //   37: astore 6
    //   39: invokestatic 71	utils/JdbcUtilsProperties:getConnection	()Ljava/sql/Connection;
    //   42: astore_3
    //   43: aload_3
    //   44: invokeinterface 77 1 0
    //   49: astore 4
    //   51: aload 4
    //   53: aload 6
    //   55: invokeinterface 137 2 0
    //   60: astore 5
    //   62: goto +106 -> 168
    //   65: aload 5
    //   67: ldc -76
    //   69: invokeinterface 182 2 0
    //   74: astore 7
    //   76: aload 5
    //   78: ldc -70
    //   80: invokeinterface 187 2 0
    //   85: astore 8
    //   87: new 46	java/lang/StringBuilder
    //   90: dup
    //   91: ldc -66
    //   93: invokespecial 50	java/lang/StringBuilder:<init>	(Ljava/lang/String;)V
    //   96: aload 8
    //   98: invokevirtual 192	java/sql/Date:getYear	()I
    //   101: sipush 1900
    //   104: iadd
    //   105: invokevirtual 53	java/lang/StringBuilder:append	(I)Ljava/lang/StringBuilder;
    //   108: ldc -63
    //   110: invokevirtual 59	java/lang/StringBuilder:append	(Ljava/lang/String;)Ljava/lang/StringBuilder;
    //   113: aload 8
    //   115: invokevirtual 195	java/sql/Date:getMonth	()I
    //   118: iconst_1
    //   119: iadd
    //   120: invokevirtual 53	java/lang/StringBuilder:append	(I)Ljava/lang/StringBuilder;
    //   123: ldc -63
    //   125: invokevirtual 59	java/lang/StringBuilder:append	(Ljava/lang/String;)Ljava/lang/StringBuilder;
    //   128: aload 8
    //   130: invokevirtual 196	java/sql/Date:getDate	()I
    //   133: invokevirtual 53	java/lang/StringBuilder:append	(I)Ljava/lang/StringBuilder;
    //   136: invokevirtual 67	java/lang/StringBuilder:toString	()Ljava/lang/String;
    //   139: astore 9
    //   141: aload_2
    //   142: new 46	java/lang/StringBuilder
    //   145: dup
    //   146: aload 7
    //   148: invokestatic 197	java/lang/String:valueOf	(Ljava/lang/Object;)Ljava/lang/String;
    //   151: invokespecial 50	java/lang/StringBuilder:<init>	(Ljava/lang/String;)V
    //   154: aload 9
    //   156: invokevirtual 59	java/lang/StringBuilder:append	(Ljava/lang/String;)Ljava/lang/StringBuilder;
    //   159: invokevirtual 67	java/lang/StringBuilder:toString	()Ljava/lang/String;
    //   162: invokeinterface 201 2 0
    //   167: pop
    //   168: aload 5
    //   170: invokeinterface 141 1 0
    //   175: ifne -110 -> 65
    //   178: goto +33 -> 211
    //   181: astore 7
    //   183: aload 7
    //   185: invokevirtual 89	java/sql/SQLException:printStackTrace	()V
    //   188: new 94	java/lang/RuntimeException
    //   191: dup
    //   192: ldc -101
    //   194: invokespecial 98	java/lang/RuntimeException:<init>	(Ljava/lang/String;)V
    //   197: athrow
    //   198: astore 10
    //   200: aload_3
    //   201: aload 4
    //   203: aload 5
    //   205: invokestatic 152	utils/JdbcUtilsProperties:close	(Ljava/sql/Connection;Ljava/sql/Statement;Ljava/sql/ResultSet;)V
    //   208: aload 10
    //   210: athrow
    //   211: aload_3
    //   212: aload 4
    //   214: aload 5
    //   216: invokestatic 152	utils/JdbcUtilsProperties:close	(Ljava/sql/Connection;Ljava/sql/Statement;Ljava/sql/ResultSet;)V
    //   219: aload_2
    //   220: invokestatic 207	java/util/Collections:reverse	(Ljava/util/List;)V
    //   223: aload_2
    //   224: areturn
    // Line number table:
    //   Java source line #87	-> byte code offset #0
    //   Java source line #88	-> byte code offset #8
    //   Java source line #89	-> byte code offset #10
    //   Java source line #90	-> byte code offset #13
    //   Java source line #91	-> byte code offset #16
    //   Java source line #92	-> byte code offset #39
    //   Java source line #94	-> byte code offset #43
    //   Java source line #95	-> byte code offset #51
    //   Java source line #96	-> byte code offset #62
    //   Java source line #97	-> byte code offset #65
    //   Java source line #98	-> byte code offset #76
    //   Java source line #99	-> byte code offset #87
    //   Java source line #100	-> byte code offset #141
    //   Java source line #96	-> byte code offset #168
    //   Java source line #102	-> byte code offset #181
    //   Java source line #103	-> byte code offset #183
    //   Java source line #104	-> byte code offset #188
    //   Java source line #105	-> byte code offset #198
    //   Java source line #106	-> byte code offset #200
    //   Java source line #107	-> byte code offset #208
    //   Java source line #106	-> byte code offset #211
    //   Java source line #108	-> byte code offset #219
    //   Java source line #109	-> byte code offset #223
    // Local variable table:
    //   start	length	slot	name	signature
    //   0	225	0	this	FileDaoImpl
    //   0	225	1	storeId	int
    //   7	217	2	list	java.util.List<String>
    //   9	203	3	con	Connection
    //   11	202	4	statement	Statement
    //   14	201	5	rs	ResultSet
    //   37	17	6	sql	String
    //   74	73	7	name	String
    //   181	3	7	e	SQLException
    //   85	44	8	date	java.sql.Date
    //   139	16	9	time	String
    //   198	11	10	localObject	Object
    // Exception table:
    //   from	to	target	type
    //   43	178	181	java/sql/SQLException
    //   43	198	198	finally
  }
  
  /* Error */
  public String getFilePath(String name, java.sql.Date date, int storeId)
  {
    // Byte code:
    //   0: ldc -36
    //   2: astore 4
    //   4: aconst_null
    //   5: astore 5
    //   7: aconst_null
    //   8: astore 6
    //   10: aconst_null
    //   11: astore 7
    //   13: new 46	java/lang/StringBuilder
    //   16: dup
    //   17: ldc -34
    //   19: invokespecial 50	java/lang/StringBuilder:<init>	(Ljava/lang/String;)V
    //   22: aload_1
    //   23: invokevirtual 59	java/lang/StringBuilder:append	(Ljava/lang/String;)Ljava/lang/StringBuilder;
    //   26: ldc -32
    //   28: invokevirtual 59	java/lang/StringBuilder:append	(Ljava/lang/String;)Ljava/lang/StringBuilder;
    //   31: aload_2
    //   32: invokevirtual 62	java/lang/StringBuilder:append	(Ljava/lang/Object;)Ljava/lang/StringBuilder;
    //   35: ldc -30
    //   37: invokevirtual 59	java/lang/StringBuilder:append	(Ljava/lang/String;)Ljava/lang/StringBuilder;
    //   40: iload_3
    //   41: invokevirtual 53	java/lang/StringBuilder:append	(I)Ljava/lang/StringBuilder;
    //   44: ldc -28
    //   46: invokevirtual 59	java/lang/StringBuilder:append	(Ljava/lang/String;)Ljava/lang/StringBuilder;
    //   49: invokevirtual 67	java/lang/StringBuilder:toString	()Ljava/lang/String;
    //   52: astore 8
    //   54: invokestatic 71	utils/JdbcUtilsProperties:getConnection	()Ljava/sql/Connection;
    //   57: astore 5
    //   59: getstatic 18	daoImpl/FileDaoImpl:logger1	Lorg/apache/log4j/Logger;
    //   62: new 46	java/lang/StringBuilder
    //   65: dup
    //   66: ldc -26
    //   68: invokespecial 50	java/lang/StringBuilder:<init>	(Ljava/lang/String;)V
    //   71: aload 8
    //   73: invokevirtual 59	java/lang/StringBuilder:append	(Ljava/lang/String;)Ljava/lang/StringBuilder;
    //   76: invokevirtual 67	java/lang/StringBuilder:toString	()Ljava/lang/String;
    //   79: invokevirtual 232	org/apache/log4j/Logger:info	(Ljava/lang/Object;)V
    //   82: aload 5
    //   84: invokeinterface 77 1 0
    //   89: astore 6
    //   91: aload 6
    //   93: aload 8
    //   95: invokeinterface 137 2 0
    //   100: astore 7
    //   102: aload 7
    //   104: invokeinterface 141 1 0
    //   109: ifeq +48 -> 157
    //   112: aload 7
    //   114: ldc -20
    //   116: invokeinterface 182 2 0
    //   121: astore 4
    //   123: goto +34 -> 157
    //   126: astore 9
    //   128: aload 9
    //   130: invokevirtual 89	java/sql/SQLException:printStackTrace	()V
    //   133: new 94	java/lang/RuntimeException
    //   136: dup
    //   137: ldc -101
    //   139: invokespecial 98	java/lang/RuntimeException:<init>	(Ljava/lang/String;)V
    //   142: athrow
    //   143: astore 10
    //   145: aload 5
    //   147: aload 6
    //   149: aload 7
    //   151: invokestatic 152	utils/JdbcUtilsProperties:close	(Ljava/sql/Connection;Ljava/sql/Statement;Ljava/sql/ResultSet;)V
    //   154: aload 10
    //   156: athrow
    //   157: aload 5
    //   159: aload 6
    //   161: aload 7
    //   163: invokestatic 152	utils/JdbcUtilsProperties:close	(Ljava/sql/Connection;Ljava/sql/Statement;Ljava/sql/ResultSet;)V
    //   166: aload 4
    //   168: areturn
    // Line number table:
    //   Java source line #114	-> byte code offset #0
    //   Java source line #115	-> byte code offset #4
    //   Java source line #116	-> byte code offset #7
    //   Java source line #117	-> byte code offset #10
    //   Java source line #118	-> byte code offset #13
    //   Java source line #119	-> byte code offset #54
    //   Java source line #120	-> byte code offset #59
    //   Java source line #122	-> byte code offset #82
    //   Java source line #123	-> byte code offset #91
    //   Java source line #124	-> byte code offset #102
    //   Java source line #125	-> byte code offset #112
    //   Java source line #127	-> byte code offset #126
    //   Java source line #128	-> byte code offset #128
    //   Java source line #129	-> byte code offset #133
    //   Java source line #130	-> byte code offset #143
    //   Java source line #131	-> byte code offset #145
    //   Java source line #132	-> byte code offset #154
    //   Java source line #131	-> byte code offset #157
    //   Java source line #133	-> byte code offset #166
    // Local variable table:
    //   start	length	slot	name	signature
    //   0	169	0	this	FileDaoImpl
    //   0	169	1	name	String
    //   0	169	2	date	java.sql.Date
    //   0	169	3	storeId	int
    //   2	165	4	path	String
    //   5	153	5	con	Connection
    //   8	152	6	statement	Statement
    //   11	151	7	rs	ResultSet
    //   52	42	8	sql	String
    //   126	3	9	e	SQLException
    //   143	12	10	localObject	Object
    // Exception table:
    //   from	to	target	type
    //   82	123	126	java/sql/SQLException
    //   82	143	143	finally
  }
  
  /* Error */
  public void deleteFile(String name, java.sql.Date date, int storeId)
  {
    // Byte code:
    //   0: new 46	java/lang/StringBuilder
    //   3: dup
    //   4: ldc -16
    //   6: invokespecial 50	java/lang/StringBuilder:<init>	(Ljava/lang/String;)V
    //   9: aload_1
    //   10: invokevirtual 59	java/lang/StringBuilder:append	(Ljava/lang/String;)Ljava/lang/StringBuilder;
    //   13: ldc -32
    //   15: invokevirtual 59	java/lang/StringBuilder:append	(Ljava/lang/String;)Ljava/lang/StringBuilder;
    //   18: aload_2
    //   19: invokevirtual 62	java/lang/StringBuilder:append	(Ljava/lang/Object;)Ljava/lang/StringBuilder;
    //   22: ldc -30
    //   24: invokevirtual 59	java/lang/StringBuilder:append	(Ljava/lang/String;)Ljava/lang/StringBuilder;
    //   27: iload_3
    //   28: invokevirtual 53	java/lang/StringBuilder:append	(I)Ljava/lang/StringBuilder;
    //   31: ldc -28
    //   33: invokevirtual 59	java/lang/StringBuilder:append	(Ljava/lang/String;)Ljava/lang/StringBuilder;
    //   36: invokevirtual 67	java/lang/StringBuilder:toString	()Ljava/lang/String;
    //   39: astore 4
    //   41: aconst_null
    //   42: astore 5
    //   44: aconst_null
    //   45: astore 6
    //   47: invokestatic 71	utils/JdbcUtilsProperties:getConnection	()Ljava/sql/Connection;
    //   50: astore 5
    //   52: aload 5
    //   54: invokeinterface 77 1 0
    //   59: astore 6
    //   61: aload 6
    //   63: aload 4
    //   65: invokeinterface 83 2 0
    //   70: pop
    //   71: goto +32 -> 103
    //   74: astore 7
    //   76: aload 7
    //   78: invokevirtual 89	java/sql/SQLException:printStackTrace	()V
    //   81: new 94	java/lang/RuntimeException
    //   84: dup
    //   85: ldc -14
    //   87: invokespecial 98	java/lang/RuntimeException:<init>	(Ljava/lang/String;)V
    //   90: athrow
    //   91: astore 8
    //   93: aload 5
    //   95: aload 6
    //   97: invokestatic 99	utils/JdbcUtilsProperties:close	(Ljava/sql/Connection;Ljava/sql/Statement;)V
    //   100: aload 8
    //   102: athrow
    //   103: aload 5
    //   105: aload 6
    //   107: invokestatic 99	utils/JdbcUtilsProperties:close	(Ljava/sql/Connection;Ljava/sql/Statement;)V
    //   110: return
    // Line number table:
    //   Java source line #138	-> byte code offset #0
    //   Java source line #139	-> byte code offset #41
    //   Java source line #140	-> byte code offset #44
    //   Java source line #141	-> byte code offset #47
    //   Java source line #143	-> byte code offset #52
    //   Java source line #144	-> byte code offset #61
    //   Java source line #145	-> byte code offset #74
    //   Java source line #146	-> byte code offset #76
    //   Java source line #147	-> byte code offset #81
    //   Java source line #148	-> byte code offset #91
    //   Java source line #149	-> byte code offset #93
    //   Java source line #150	-> byte code offset #100
    //   Java source line #149	-> byte code offset #103
    //   Java source line #151	-> byte code offset #110
    // Local variable table:
    //   start	length	slot	name	signature
    //   0	111	0	this	FileDaoImpl
    //   0	111	1	name	String
    //   0	111	2	date	java.sql.Date
    //   0	111	3	storeId	int
    //   39	25	4	sql	String
    //   42	62	5	con	Connection
    //   45	61	6	statement	Statement
    //   74	3	7	e	SQLException
    //   91	10	8	localObject	Object
    // Exception table:
    //   from	to	target	type
    //   52	71	74	java/sql/SQLException
    //   52	91	91	finally
  }
}
