package daoImpl;

import dao.StoreDao;

public class StoreDaoImpl
  implements StoreDao
{
  /* Error */
  public void addStore(entity.User user)
  {
    // Byte code:
    //   0: aconst_null
    //   1: astore_2
    //   2: aconst_null
    //   3: astore_3
    //   4: ldc 18
    //   6: astore 4
    //   8: invokestatic 20	utils/JdbcUtilsProperties:getConnection	()Ljava/sql/Connection;
    //   11: astore_2
    //   12: aload_2
    //   13: aload 4
    //   15: invokeinterface 26 2 0
    //   20: astore_3
    //   21: aload_3
    //   22: iconst_1
    //   23: aload_1
    //   24: invokevirtual 32	entity/User:getUserName	()Ljava/lang/String;
    //   27: invokeinterface 38 3 0
    //   32: aload_3
    //   33: invokeinterface 44 1 0
    //   38: istore 5
    //   40: goto +30 -> 70
    //   43: astore 5
    //   45: aload 5
    //   47: invokevirtual 48	java/sql/SQLException:printStackTrace	()V
    //   50: new 53	java/lang/RuntimeException
    //   53: dup
    //   54: ldc 55
    //   56: invokespecial 57	java/lang/RuntimeException:<init>	(Ljava/lang/String;)V
    //   59: athrow
    //   60: astore 6
    //   62: aload_2
    //   63: aload_3
    //   64: invokestatic 60	utils/JdbcUtilsProperties:close	(Ljava/sql/Connection;Ljava/sql/Statement;)V
    //   67: aload 6
    //   69: athrow
    //   70: aload_2
    //   71: aload_3
    //   72: invokestatic 60	utils/JdbcUtilsProperties:close	(Ljava/sql/Connection;Ljava/sql/Statement;)V
    //   75: return
    // Line number table:
    //   Java source line #19	-> byte code offset #0
    //   Java source line #20	-> byte code offset #2
    //   Java source line #21	-> byte code offset #4
    //   Java source line #23	-> byte code offset #8
    //   Java source line #25	-> byte code offset #12
    //   Java source line #26	-> byte code offset #21
    //   Java source line #27	-> byte code offset #32
    //   Java source line #28	-> byte code offset #43
    //   Java source line #29	-> byte code offset #45
    //   Java source line #30	-> byte code offset #50
    //   Java source line #31	-> byte code offset #60
    //   Java source line #32	-> byte code offset #62
    //   Java source line #33	-> byte code offset #67
    //   Java source line #32	-> byte code offset #70
    //   Java source line #34	-> byte code offset #75
    // Local variable table:
    //   start	length	slot	name	signature
    //   0	76	0	this	StoreDaoImpl
    //   0	76	1	user	entity.User
    //   1	70	2	con	java.sql.Connection
    //   3	69	3	pst	java.sql.PreparedStatement
    //   6	8	4	sql	String
    //   38	3	5	result	int
    //   43	3	5	e	java.sql.SQLException
    //   60	8	6	localObject	Object
    // Exception table:
    //   from	to	target	type
    //   12	40	43	java/sql/SQLException
    //   12	60	60	finally
  }
  
  /* Error */
  public entity.Store getStore(entity.User user)
  {
    // Byte code:
    //   0: new 83	entity/Store
    //   3: dup
    //   4: invokespecial 85	entity/Store:<init>	()V
    //   7: astore_2
    //   8: aconst_null
    //   9: astore_3
    //   10: aconst_null
    //   11: astore 4
    //   13: aconst_null
    //   14: astore 5
    //   16: new 86	java/lang/StringBuilder
    //   19: dup
    //   20: ldc 88
    //   22: invokespecial 90	java/lang/StringBuilder:<init>	(Ljava/lang/String;)V
    //   25: aload_1
    //   26: invokevirtual 32	entity/User:getUserName	()Ljava/lang/String;
    //   29: invokevirtual 91	java/lang/StringBuilder:append	(Ljava/lang/String;)Ljava/lang/StringBuilder;
    //   32: ldc 95
    //   34: invokevirtual 91	java/lang/StringBuilder:append	(Ljava/lang/String;)Ljava/lang/StringBuilder;
    //   37: invokevirtual 97	java/lang/StringBuilder:toString	()Ljava/lang/String;
    //   40: astore 6
    //   42: invokestatic 20	utils/JdbcUtilsProperties:getConnection	()Ljava/sql/Connection;
    //   45: astore_3
    //   46: aload_3
    //   47: invokeinterface 100 1 0
    //   52: astore 4
    //   54: aload 4
    //   56: aload 6
    //   58: invokeinterface 104 2 0
    //   63: astore 5
    //   65: aload 5
    //   67: invokeinterface 110 1 0
    //   72: ifeq +94 -> 166
    //   75: aload_2
    //   76: aload 5
    //   78: ldc 116
    //   80: invokeinterface 118 2 0
    //   85: invokevirtual 122	entity/Store:setStoreId	(I)V
    //   88: aload_2
    //   89: aload 5
    //   91: ldc 126
    //   93: invokeinterface 118 2 0
    //   98: invokevirtual 128	entity/Store:setMaxSize	(I)V
    //   101: aload_2
    //   102: aload 5
    //   104: ldc -125
    //   106: invokeinterface 118 2 0
    //   111: invokevirtual 133	entity/Store:setCurSize	(I)V
    //   114: aload_2
    //   115: aload_1
    //   116: invokevirtual 32	entity/User:getUserName	()Ljava/lang/String;
    //   119: invokevirtual 136	entity/Store:setUserName	(Ljava/lang/String;)V
    //   122: aload_2
    //   123: new 139	java/util/ArrayList
    //   126: dup
    //   127: invokespecial 141	java/util/ArrayList:<init>	()V
    //   130: invokevirtual 142	entity/Store:setFilesPath	(Ljava/util/List;)V
    //   133: goto +33 -> 166
    //   136: astore 7
    //   138: aload 7
    //   140: invokevirtual 48	java/sql/SQLException:printStackTrace	()V
    //   143: new 53	java/lang/RuntimeException
    //   146: dup
    //   147: ldc -110
    //   149: invokespecial 57	java/lang/RuntimeException:<init>	(Ljava/lang/String;)V
    //   152: athrow
    //   153: astore 8
    //   155: aload_3
    //   156: aload 4
    //   158: aload 5
    //   160: invokestatic 148	utils/JdbcUtilsProperties:close	(Ljava/sql/Connection;Ljava/sql/Statement;Ljava/sql/ResultSet;)V
    //   163: aload 8
    //   165: athrow
    //   166: aload_3
    //   167: aload 4
    //   169: aload 5
    //   171: invokestatic 148	utils/JdbcUtilsProperties:close	(Ljava/sql/Connection;Ljava/sql/Statement;Ljava/sql/ResultSet;)V
    //   174: aload_2
    //   175: areturn
    // Line number table:
    //   Java source line #38	-> byte code offset #0
    //   Java source line #39	-> byte code offset #8
    //   Java source line #40	-> byte code offset #10
    //   Java source line #41	-> byte code offset #13
    //   Java source line #42	-> byte code offset #16
    //   Java source line #43	-> byte code offset #42
    //   Java source line #45	-> byte code offset #46
    //   Java source line #46	-> byte code offset #54
    //   Java source line #47	-> byte code offset #65
    //   Java source line #48	-> byte code offset #75
    //   Java source line #49	-> byte code offset #88
    //   Java source line #50	-> byte code offset #101
    //   Java source line #51	-> byte code offset #114
    //   Java source line #52	-> byte code offset #122
    //   Java source line #54	-> byte code offset #136
    //   Java source line #55	-> byte code offset #138
    //   Java source line #56	-> byte code offset #143
    //   Java source line #57	-> byte code offset #153
    //   Java source line #58	-> byte code offset #155
    //   Java source line #59	-> byte code offset #163
    //   Java source line #58	-> byte code offset #166
    //   Java source line #60	-> byte code offset #174
    // Local variable table:
    //   start	length	slot	name	signature
    //   0	176	0	this	StoreDaoImpl
    //   0	176	1	user	entity.User
    //   7	168	2	store	entity.Store
    //   9	158	3	con	java.sql.Connection
    //   11	157	4	statement	java.sql.Statement
    //   14	156	5	rs	java.sql.ResultSet
    //   40	17	6	sql	String
    //   136	3	7	e	java.sql.SQLException
    //   153	11	8	localObject	Object
    // Exception table:
    //   from	to	target	type
    //   46	133	136	java/sql/SQLException
    //   46	153	153	finally
  }
  
  /* Error */
  public void upDateCurSize(entity.Store store)
  {
    // Byte code:
    //   0: aload_1
    //   1: invokevirtual 159	entity/Store:getCurSize	()I
    //   4: iconst_1
    //   5: iadd
    //   6: istore_2
    //   7: new 86	java/lang/StringBuilder
    //   10: dup
    //   11: ldc -94
    //   13: invokespecial 90	java/lang/StringBuilder:<init>	(Ljava/lang/String;)V
    //   16: iload_2
    //   17: invokevirtual 164	java/lang/StringBuilder:append	(I)Ljava/lang/StringBuilder;
    //   20: ldc -89
    //   22: invokevirtual 91	java/lang/StringBuilder:append	(Ljava/lang/String;)Ljava/lang/StringBuilder;
    //   25: aload_1
    //   26: invokevirtual 169	entity/Store:getStoreId	()I
    //   29: invokevirtual 164	java/lang/StringBuilder:append	(I)Ljava/lang/StringBuilder;
    //   32: ldc 95
    //   34: invokevirtual 91	java/lang/StringBuilder:append	(Ljava/lang/String;)Ljava/lang/StringBuilder;
    //   37: invokevirtual 97	java/lang/StringBuilder:toString	()Ljava/lang/String;
    //   40: astore_3
    //   41: aconst_null
    //   42: astore 4
    //   44: aconst_null
    //   45: astore 5
    //   47: invokestatic 20	utils/JdbcUtilsProperties:getConnection	()Ljava/sql/Connection;
    //   50: astore 4
    //   52: aload 4
    //   54: invokeinterface 100 1 0
    //   59: astore 5
    //   61: aload 5
    //   63: aload_3
    //   64: invokeinterface 172 2 0
    //   69: pop
    //   70: goto +32 -> 102
    //   73: astore 6
    //   75: aload 6
    //   77: invokevirtual 48	java/sql/SQLException:printStackTrace	()V
    //   80: new 53	java/lang/RuntimeException
    //   83: dup
    //   84: ldc -82
    //   86: invokespecial 57	java/lang/RuntimeException:<init>	(Ljava/lang/String;)V
    //   89: athrow
    //   90: astore 7
    //   92: aload 4
    //   94: aload 5
    //   96: invokestatic 60	utils/JdbcUtilsProperties:close	(Ljava/sql/Connection;Ljava/sql/Statement;)V
    //   99: aload 7
    //   101: athrow
    //   102: aload 4
    //   104: aload 5
    //   106: invokestatic 60	utils/JdbcUtilsProperties:close	(Ljava/sql/Connection;Ljava/sql/Statement;)V
    //   109: return
    // Line number table:
    //   Java source line #65	-> byte code offset #0
    //   Java source line #66	-> byte code offset #7
    //   Java source line #67	-> byte code offset #41
    //   Java source line #68	-> byte code offset #44
    //   Java source line #69	-> byte code offset #47
    //   Java source line #71	-> byte code offset #52
    //   Java source line #72	-> byte code offset #61
    //   Java source line #73	-> byte code offset #73
    //   Java source line #74	-> byte code offset #75
    //   Java source line #75	-> byte code offset #80
    //   Java source line #76	-> byte code offset #90
    //   Java source line #77	-> byte code offset #92
    //   Java source line #78	-> byte code offset #99
    //   Java source line #77	-> byte code offset #102
    //   Java source line #79	-> byte code offset #109
    // Local variable table:
    //   start	length	slot	name	signature
    //   0	110	0	this	StoreDaoImpl
    //   0	110	1	store	entity.Store
    //   6	11	2	newSize	int
    //   40	24	3	sql	String
    //   42	61	4	con	java.sql.Connection
    //   45	60	5	statement	java.sql.Statement
    //   73	3	6	e	java.sql.SQLException
    //   90	10	7	localObject	Object
    // Exception table:
    //   from	to	target	type
    //   52	70	73	java/sql/SQLException
    //   52	90	90	finally
  }
  
  /* Error */
  public void deleteFile(entity.Store store)
  {
    // Byte code:
    //   0: aload_1
    //   1: invokevirtual 159	entity/Store:getCurSize	()I
    //   4: iconst_1
    //   5: isub
    //   6: istore_2
    //   7: new 86	java/lang/StringBuilder
    //   10: dup
    //   11: ldc -94
    //   13: invokespecial 90	java/lang/StringBuilder:<init>	(Ljava/lang/String;)V
    //   16: iload_2
    //   17: invokevirtual 164	java/lang/StringBuilder:append	(I)Ljava/lang/StringBuilder;
    //   20: ldc -89
    //   22: invokevirtual 91	java/lang/StringBuilder:append	(Ljava/lang/String;)Ljava/lang/StringBuilder;
    //   25: aload_1
    //   26: invokevirtual 169	entity/Store:getStoreId	()I
    //   29: invokevirtual 164	java/lang/StringBuilder:append	(I)Ljava/lang/StringBuilder;
    //   32: ldc 95
    //   34: invokevirtual 91	java/lang/StringBuilder:append	(Ljava/lang/String;)Ljava/lang/StringBuilder;
    //   37: invokevirtual 97	java/lang/StringBuilder:toString	()Ljava/lang/String;
    //   40: astore_3
    //   41: aconst_null
    //   42: astore 4
    //   44: aconst_null
    //   45: astore 5
    //   47: invokestatic 20	utils/JdbcUtilsProperties:getConnection	()Ljava/sql/Connection;
    //   50: astore 4
    //   52: aload 4
    //   54: invokeinterface 100 1 0
    //   59: astore 5
    //   61: aload 5
    //   63: aload_3
    //   64: invokeinterface 172 2 0
    //   69: pop
    //   70: goto +32 -> 102
    //   73: astore 6
    //   75: aload 6
    //   77: invokevirtual 48	java/sql/SQLException:printStackTrace	()V
    //   80: new 53	java/lang/RuntimeException
    //   83: dup
    //   84: ldc -82
    //   86: invokespecial 57	java/lang/RuntimeException:<init>	(Ljava/lang/String;)V
    //   89: athrow
    //   90: astore 7
    //   92: aload 4
    //   94: aload 5
    //   96: invokestatic 60	utils/JdbcUtilsProperties:close	(Ljava/sql/Connection;Ljava/sql/Statement;)V
    //   99: aload 7
    //   101: athrow
    //   102: aload 4
    //   104: aload 5
    //   106: invokestatic 60	utils/JdbcUtilsProperties:close	(Ljava/sql/Connection;Ljava/sql/Statement;)V
    //   109: return
    // Line number table:
    //   Java source line #83	-> byte code offset #0
    //   Java source line #84	-> byte code offset #7
    //   Java source line #85	-> byte code offset #41
    //   Java source line #86	-> byte code offset #44
    //   Java source line #87	-> byte code offset #47
    //   Java source line #89	-> byte code offset #52
    //   Java source line #90	-> byte code offset #61
    //   Java source line #91	-> byte code offset #73
    //   Java source line #92	-> byte code offset #75
    //   Java source line #93	-> byte code offset #80
    //   Java source line #94	-> byte code offset #90
    //   Java source line #95	-> byte code offset #92
    //   Java source line #96	-> byte code offset #99
    //   Java source line #95	-> byte code offset #102
    //   Java source line #97	-> byte code offset #109
    // Local variable table:
    //   start	length	slot	name	signature
    //   0	110	0	this	StoreDaoImpl
    //   0	110	1	store	entity.Store
    //   6	11	2	newSize	int
    //   40	24	3	sql	String
    //   42	61	4	con	java.sql.Connection
    //   45	60	5	statement	java.sql.Statement
    //   73	3	6	e	java.sql.SQLException
    //   90	10	7	localObject	Object
    // Exception table:
    //   from	to	target	type
    //   52	70	73	java/sql/SQLException
    //   52	90	90	finally
  }
}
